arc_dialect_json.py
arc_superset_dialect-1.3.3.dist-info/METADATA
arc_superset_dialect-1.3.3.dist-info/WHEEL
arc_superset_dialect-1.3.3.dist-info/entry_points.txt
arc_superset_dialect-1.3.3.dist-info/top_level.txt
arc_superset_dialect-1.3.3.dist-info/RECORD
