Metadata-Version: 2.4
Name: arc-superset-dialect
Version: 1.3.3
Summary: SQLAlchemy dialect for Arc time-series database with multi-database support for Apache Superset
Home-page: https://github.com/basekick-labs/arc-superset-dialect
Author: Arc Core Team
Author-email: support@basekick.net
Project-URL: Bug Tracker, https://github.com/basekick-labs/arc-superset-dialect/issues
Project-URL: Documentation, https://github.com/basekick-labs/arc-superset-dialect
Project-URL: Source Code, https://github.com/basekick-labs/arc-superset-dialect
Keywords: arc superset sqlalchemy dialect timeseries database
Classifier: Development Status :: 4 - Beta
Classifier: Intended Audience :: Developers
Classifier: Topic :: Database
Classifier: License :: OSI Approved :: GNU Affero General Public License v3
Classifier: Programming Language :: Python :: 3
Classifier: Programming Language :: Python :: 3.8
Classifier: Programming Language :: Python :: 3.9
Classifier: Programming Language :: Python :: 3.10
Classifier: Programming Language :: Python :: 3.11
Requires-Python: >=3.8
Requires-Dist: SQLAlchemy<3.0.0,>=1.4.0
Requires-Dist: requests>=2.31.0
Dynamic: author
Dynamic: author-email
Dynamic: classifier
Dynamic: description
Dynamic: description-content-type
Dynamic: home-page
Dynamic: keywords
Dynamic: project-url
Dynamic: requires-dist
Dynamic: requires-python
Dynamic: summary
